example/.pytest_cache/.gitignore
example/.pytest_cache/CACHEDIR.TAG
example/.pytest_cache/README.md
example/.pytest_cache/v/cache/nodeids
example/.pytest_cache/v/cache/stepwise
example/__init__.py
example/example.py
example/example_with_subscription.py
rich_strawberry/__init__.py
rich_strawberry/extension.py
rich_strawberry/logger.py
rich_strawberry-0.2.0.dist-info/WHEEL
rich_strawberry-0.2.0.dist-info/METADATA
rich_strawberry-0.2.0.dist-info/licenses/LICENSE
rich_strawberry-0.2.0.dist-info/RECORD
