Metadata-Version: 2.1
Name: rich-strawberry
Version: 0.2.0
License: MIT
Author-email: zlira <olesia.hr@gmail.com>
Requires-Python: >=3.9
Requires-Dist: rich>=12.5.1
Requires-Dist: strawberry-graphql[cli]>=0.154.0
